docs/conf.py
omnixai_community/__init__.py
omnixai_community/data/__init__.py
omnixai_community/data/base.py
omnixai_community/data/image.py
omnixai_community/data/multi_inputs.py
omnixai_community/data/tabular.py
omnixai_community/data/text.py
omnixai_community/data/timeseries.py
omnixai_community/deployment/__init__.py
omnixai_community/deployment/bentoml/__init__.py
omnixai_community/deployment/bentoml/omnixai.py
omnixai_community/explainers/__init__.py
omnixai_community/explainers/base.py
omnixai_community/explainers/data/__init__.py
omnixai_community/explainers/data/auto.py
omnixai_community/explainers/data/chi_square.py
omnixai_community/explainers/data/correlation.py
omnixai_community/explainers/data/imbalance.py
omnixai_community/explainers/data/mutual_info.py
omnixai_community/explainers/nlp/__init__.py
omnixai_community/explainers/nlp/auto.py
omnixai_community/explainers/nlp/agnostic/__init__.py
omnixai_community/explainers/nlp/agnostic/l2x.py
omnixai_community/explainers/nlp/agnostic/lime.py
omnixai_community/explainers/nlp/agnostic/shap.py
omnixai_community/explainers/nlp/counterfactual/__init__.py
omnixai_community/explainers/nlp/counterfactual/polyjuice.py
omnixai_community/explainers/nlp/specific/__init__.py
omnixai_community/explainers/nlp/specific/ig.py
omnixai_community/explainers/prediction/__init__.py
omnixai_community/explainers/prediction/auto.py
omnixai_community/explainers/ranking/__init__.py
omnixai_community/explainers/ranking/agnostic/__init__.py
omnixai_community/explainers/ranking/agnostic/permutation.py
omnixai_community/explainers/ranking/agnostic/validity.py
omnixai_community/explainers/ranking/counterfactual/__init__.py
omnixai_community/explainers/ranking/counterfactual/mace.py
omnixai_community/explainers/tabular/__init__.py
omnixai_community/explainers/tabular/auto.py
omnixai_community/explainers/tabular/base.py
omnixai_community/explainers/tabular/agnostic/__init__.py
omnixai_community/explainers/tabular/agnostic/ale.py
omnixai_community-1.3.2.3.dist-info/LICENSE
omnixai_community-1.3.2.3.dist-info/METADATA
omnixai_community-1.3.2.3.dist-info/WHEEL
omnixai_community-1.3.2.3.dist-info/top_level.txt
omnixai_community-1.3.2.3.dist-info/RECORD
